{"trackers":[{"listIntervals":[{"inProgress":false,"startTime":"2020-11-20T13:21:32.497","endTime":"2020-11-20T13:21:38.383"},{"inProgress":false,"startTime":"2020-11-20T13:21:54.577","endTime":"2020-11-20T13:21:58.494"}],"name":"Transportation","active":false,"startTime":"2020-11-20T13:21:32.497","endTime":"2020-11-20T13:21:58.494"},{"trackers":[{"trackers":[{"listIntervals":[{"inProgress":false,"startTime":"2020-11-20T13:21:40.537","endTime":"2020-11-20T13:21:50.442"}],"name":"First List","active":false,"startTime":"2020-11-20T13:21:40.537","endTime":"2020-11-20T13:21:50.442"},{"listIntervals":[{"inProgress":false,"startTime":"2020-11-20T13:21:46.543","endTime":"2020-11-20T13:21:52.457"}],"name":"Second List","active":false,"startTime":"2020-11-20T13:21:46.543","endTime":"2020-11-20T13:21:52.457"}],"name":"Problems","startTime":"2020-11-20T13:21:40.537","endTime":"2020-11-20T13:21:52.457"}],"name":"Software Design","startTime":"2020-11-20T13:21:40.537","endTime":"2020-11-20T13:21:52.457"}],"name":"root","startTime":"2020-11-20T13:21:32.497","endTime":"2020-11-20T13:21:58.494"}